mcubes/__init__.py
mcubes/_mcubes.cpython-313-x86_64-linux-gnu.so
mcubes/exporter.py
mcubes/numpy_smoothing.py
mcubes/smoothing.py
mcubes/version.py
mvpymcubes-0.1.6.dist-info/METADATA
mvpymcubes-0.1.6.dist-info/WHEEL
mvpymcubes-0.1.6.dist-info/top_level.txt
mvpymcubes-0.1.6.dist-info/RECORD
mvpymcubes-0.1.6.dist-info/licenses/LICENSE
